windtunnel/__init__.py
windtunnel/controller.py
windtunnel/errors.py
windtunnel/helpers.py
windtunnel/model.py
windtunnel/view.py
windtunnel-1.0.dist-info/LICENCE
windtunnel-1.0.dist-info/METADATA
windtunnel-1.0.dist-info/WHEEL
windtunnel-1.0.dist-info/top_level.txt
windtunnel-1.0.dist-info/RECORD
