Metadata-Version: 2.1
Name: windtunnel
Version: 1.0
Summary: Créé le shift avec le staff et les timeslots donnés
Home-page: https://github.com/tperrinweembi/tunn3l-shift
Author: thomas
Author-email: anathopee.gestion@gmail.com
Classifier: Programming Language :: Python :: 3
Classifier: License :: OSI Approved :: MIT License
Classifier: Operating System :: OS Independent
Requires-Python: >=3.12
License-File: LICENCE
Requires-Dist: beautifulsoup4 ==4.12.3
Requires-Dist: browser-cookie3 ==0.19.1
Requires-Dist: certifi ==2024.6.2
Requires-Dist: charset-normalizer ==3.3.2
Requires-Dist: idna ==3.7
Requires-Dist: lz4 ==4.3.3
Requires-Dist: markdown-it-py ==3.0.0
Requires-Dist: mdurl ==0.1.2
Requires-Dist: numpy ==2.0.0
Requires-Dist: pandas ==2.2.2
Requires-Dist: pycryptodomex ==3.20.0
Requires-Dist: Pygments ==2.18.0
Requires-Dist: python-dateutil ==2.9.0.post0
Requires-Dist: python-dotenv ==1.0.1
Requires-Dist: pytz ==2024.1
Requires-Dist: requests ==2.32.3
Requires-Dist: rich ==13.7.1
Requires-Dist: setuptools ==70.2.0
Requires-Dist: six ==1.16.0
Requires-Dist: soupsieve ==2.5
Requires-Dist: tabulate ==0.9.0
Requires-Dist: tzdata ==2024.1
Requires-Dist: urllib3 ==2.2.2
